mcp_multi_cloud/__init__.py
mcp_multi_cloud/cloud.py
mcp_multi_cloud/compute.py
mcp_multi_cloud/main.py
mcp_multi_cloud/storage.py
mcp_multi_cloud-0.1.0.dist-info/METADATA
mcp_multi_cloud-0.1.0.dist-info/WHEEL
mcp_multi_cloud-0.1.0.dist-info/RECORD
