Metadata-Version: 2.4
Name: mcp_multi_cloud
Version: 0.1.0
Summary: MCP Server to interact with multiple clouds based on Anthropic's Model Context Protocol
Author-email: Bhavik Shah <bhavik1st@gmail.com>
License: MIT License
Classifier: Development Status :: 4 - Beta
Classifier: Intended Audience :: Developers
Classifier: License :: OSI Approved :: MIT License
Classifier: Programming Language :: Python :: 3
Classifier: Programming Language :: Python :: 3.11
Classifier: Programming Language :: Python :: 3.12
Classifier: Programming Language :: Python :: 3.13
Requires-Python: >=3.11
Requires-Dist: apache-libcloud>=3.8.0
Requires-Dist: httpx>=0.28.1
Requires-Dist: mcp==1.6.0
Requires-Dist: mcp[cli]>=1.6.0
